django_imap_backend/__init__.py
django_imap_backend/backend.py
django_imap_backend/client.py
django_imap_backend/version.py
django_imap_backend-0.2.3.dist-info/LICENSE
django_imap_backend-0.2.3.dist-info/METADATA
django_imap_backend-0.2.3.dist-info/WHEEL
django_imap_backend-0.2.3.dist-info/top_level.txt
django_imap_backend-0.2.3.dist-info/RECORD
