Metadata-Version: 2.1
Name: django-imap-backend
Version: 0.2.3
Summary: IMAP backend for Django mail package
Home-page: https://github.com/Sibyx/django_imap_backend
Author: Jakub Dubec
Author-email: jakub.dubec@gmail.com
License: MIT
Keywords: django,mail,imap,backend,mailbox
Platform: UNKNOWN
Classifier: Development Status :: 4 - Beta
Classifier: Programming Language :: Python
Classifier: Programming Language :: Python :: 3.6
Classifier: Programming Language :: Python :: 3.7
Classifier: Programming Language :: Python :: 3.8
Classifier: Programming Language :: Python :: Implementation :: PyPy
Classifier: Framework :: Django :: 2.0
Classifier: Framework :: Django :: 2.1
Classifier: Framework :: Django :: 2.2
Classifier: Framework :: Django :: 3.0
Classifier: Intended Audience :: Developers
Classifier: License :: OSI Approved :: MIT License
Classifier: Operating System :: OS Independent
Classifier: Topic :: Internet :: WWW/HTTP
Classifier: Topic :: Internet :: WWW/HTTP :: HTTP Servers
Classifier: Topic :: Software Development :: Libraries :: Python Modules
Classifier: Topic :: Communications :: Email :: Post-Office :: IMAP
Classifier: Topic :: Utilities
Classifier: Environment :: Web Environment
